iamjjintta/__init__.py
iamjjintta/github.py
iamjjintta_pygithub-0.0.1.dist-info/LICENSE
iamjjintta_pygithub-0.0.1.dist-info/METADATA
iamjjintta_pygithub-0.0.1.dist-info/WHEEL
iamjjintta_pygithub-0.0.1.dist-info/top_level.txt
iamjjintta_pygithub-0.0.1.dist-info/RECORD
